starterkit_ci/__init__.py
starterkit_ci/sphinx_config/__init__.py
starterkit_ci/sphinx_config/fix_markdown_file_downloads.py
starterkit_ci/sphinx_config/panels.py
starterkit_ci/sphinx_config/_static/panels.css
starterkit_ci/sphinx_config/_static/panels.js
starterkit_ci-0.1.2.dist-info/LICENSE
starterkit_ci-0.1.2.dist-info/METADATA
starterkit_ci-0.1.2.dist-info/WHEEL
starterkit_ci-0.1.2.dist-info/entry_points.txt
starterkit_ci-0.1.2.dist-info/top_level.txt
starterkit_ci-0.1.2.dist-info/RECORD
