Metadata-Version: 2.1
Name: starterkit-ci
Version: 0.1.2
Summary: Helpers for Starterkit Continuous Integration
Home-page: https://github.com/lhcb/starterkit_ci
Author: LHCb Starterkit
License: UNKNOWN
Project-URL: Bug Reports, https://github.com/lhcb/starterkit_ci/issues
Project-URL: Source, https://github.com/lhcb/starterkit_ci
Keywords: Starterkit
Platform: UNKNOWN
Classifier: Development Status :: 4 - Beta
Classifier: License :: OSI Approved :: BSD License
Classifier: Programming Language :: Python :: 3
Classifier: Programming Language :: Python :: 3.6
Classifier: Programming Language :: Python :: 3.7
Classifier: Programming Language :: Python :: 3.8
Requires-Python: >=3.6
Requires-Dist: sphinx
Requires-Dist: sphinx-rtd-theme
Requires-Dist: recommonmark
Requires-Dist: sphinx-markdown-parser
Requires-Dist: nbsphinx
